{
	"schema_version": 1,
	"quilt_loader": {
		"group": "com.mentoskapraha",
		"id": "clear_skies_reforged",
		"version": "${version}",
		"metadata": {
			"name": "Clear Skies Reforged",
			"description": "",
			"contributors": {
				"MentoskaPraha": "Owner"
			},
			"contact": {
				"homepage": "https://modrinth.com/mod/OiK47KVl",
				"issues": "https://github.com/MentoskaPraha/clear-skies-reforged/issues",
				"sources": "https://github.com/MentoskaPraha/clear-skies-reforged"
			},
			"icon": "assets/clear_skies_reforged/icon.png"
		},
		"depends": [
			{
				"id": "quilt_loader",
				"versions": ">=0.21.2-"
			},
			{
				"id": "minecraft",
				"versions": ">=1.19.2"
			}
		]
	},
	"mixin": "clear_skies_reforged.mixins.json"
}